{"cameraMode":{"drawMode":0,"name":"Shaded","section":"Shading Mode"},"sceneLighting":true,"audioPlay":false,"sceneViewState":{"m_AlwaysRefresh":true,"showFog":true,"showSkybox":false,"showFlares":true,"showImageEffects":true,"showParticleSystems":true,"showVisualEffectGraphs":true,"m_FxEnabled":true},"in2DMode":false,"pivot":{"x":1122.072265625,"y":996.40380859375,"z":415.8848571777344},"rotation":{"x":-0.018928222358226777,"y":-0.8986923098564148,"z":0.43430858850479128,"w":-0.03052874095737934},"size":80.62257385253906,"orthographic":false}